gopher_robot_version/__init__.py
gopher_robot_version/ros_packages.py
gopher_robot_version/sys_packages.py
gopher_robot_version/writer.py
gopher_robot_version-0.13.data/scripts/gopher_robot_version
gopher_robot_version-0.13.dist-info/DESCRIPTION.rst
gopher_robot_version-0.13.dist-info/METADATA
gopher_robot_version-0.13.dist-info/RECORD
gopher_robot_version-0.13.dist-info/WHEEL
gopher_robot_version-0.13.dist-info/metadata.json
gopher_robot_version-0.13.dist-info/top_level.txt
