Metadata-Version: 2.0
Name: gopher-robot-version
Version: 0.13
Summary: Create a file containing the name and version of various ROS and system packages
Home-page: https://github.com/yotabits/gopher_robot_version
Author: Thomas Kostas
Author-email: tkostas75@gmail.com
License: MIT
Platform: UNKNOWN
Classifier: Development Status :: 3 - Alpha
Classifier: Intended Audience :: Developers
Classifier: Topic :: Software Development :: Build Tools
Classifier: License :: OSI Approved :: MIT License
Classifier: Programming Language :: Python :: 2.7
